bitfieldrw/__init__.py
bitfieldrw/core.py
bitfieldrw-0.1.1.dist-info/METADATA
bitfieldrw-0.1.1.dist-info/WHEEL
bitfieldrw-0.1.1.dist-info/licenses/LICENSE
bitfieldrw-0.1.1.dist-info/RECORD
