Metadata-Version: 2.4
Name: bitfieldrw
Version: 0.1.1
Summary: A Python library for reading and writing bit fields with type annotations
Project-URL: Homepage, https://github.com/DawnMagnet/bitfieldrw
Project-URL: Documentation, https://github.com/DawnMagnet/bitfieldrw#readme
Project-URL: Repository, https://github.com/DawnMagnet/bitfieldrw.git
Project-URL: Bug Tracker, https://github.com/DawnMagnet/bitfieldrw/issues
Author-email: DawnMagnet <dawnmagnet@example.com>
Maintainer-email: DawnMagnet <dawnmagnet@example.com>
License-Expression: MIT
License-File: LICENSE
Keywords: binary,bitfield,embedded,networking,protocol,serialization,struct
Classifier: Development Status :: 4 - Beta
Classifier: Intended Audience :: Developers
Classifier: License :: OSI Approved :: MIT License
Classifier: Operating System :: OS Independent
Classifier: Programming Language :: Python :: 3
Classifier: Programming Language :: Python :: 3.8
Classifier: Programming Language :: Python :: 3.9
Classifier: Programming Language :: Python :: 3.10
Classifier: Programming Language :: Python :: 3.11
Classifier: Programming Language :: Python :: 3.12
Classifier: Programming Language :: Python :: 3.13
Classifier: Topic :: Software Development :: Embedded Systems
Classifier: Topic :: Software Development :: Libraries :: Python Modules
Classifier: Topic :: System :: Networking
Classifier: Typing :: Typed
Requires-Python: >=3.8
Provides-Extra: dev
Requires-Dist: black; extra == 'dev'
Requires-Dist: build; extra == 'dev'
Requires-Dist: mypy; extra == 'dev'
Requires-Dist: ruff; extra == 'dev'
Requires-Dist: twine; extra == 'dev'
